pidetect/__init__.py
pidetect/detector.py
pidetect/so/libdetect.so
pidetect/so/libdetect.so.2.0
pidetect-2.2.0.dist-info/METADATA
pidetect-2.2.0.dist-info/WHEEL
pidetect-2.2.0.dist-info/top_level.txt
pidetect-2.2.0.dist-info/RECORD
