Metadata-Version: 2.1
Name: pidetect
Version: 2.2.0
Summary: python image detect lib
Classifier: Programming Language :: Python :: 3.6
